{
    "country_code": "AT",
    "country_name": "Austria",
    "system_name": "JMK",
    "display_name": "AT - JMK",
    "valid_ratings": ["0", "6", "10", "12", "14", "16", "18"],
    "default_prefix": "AT:",
    "inference_countries": ["DE", "NL", "BE", "FR", "GB", "DK", "SE", "US"],
    "mappings": {
        "DE": {
            "0": "0", "6": "6", "12": "12", "16": "16", "18": "18"
        },
        "NL": {
            "AL": "0", "6": "6", "9": "10", "12": "12",
            "14": "14", "16": "16", "18": "18"
        },
        "BE": {
            "AL": "0", "6": "6", "9": "10", "12": "12",
            "14": "14", "16": "16", "18": "18"
        },
        "FR": {
            "U": "0", "10": "10", "12": "12", "16": "16", "18": "18"
        },
        "GB": {
            "U": "0", "PG": "6", "12": "12", "12A": "12",
            "15": "16", "18": "18", "R18": "18"
        },
        "DK": {
            "A": "0", "7": "6", "11": "12", "15": "16"
        },
        "SE": {
            "Btl": "0", "7": "6", "11": "12", "15": "16"
        },
        "US": {
            "G": "0", "PG": "6", "PG-13": "12",
            "R": "16", "NC-17": "18",
            "TV-Y": "0", "TV-Y7": "6", "TV-G": "0",
            "TV-PG": "10", "TV-14": "14", "TV-MA": "16"
        }
    }
}
